MANIFEST.in
README.rst
setup.cfg
setup.py
tox.ini
sphinxdocs/CHANGES.rst
sphinxdocs/README.rst
sphinxdocs/api.rst
sphinxdocs/conf.py
sphinxdocs/index.rst
src/fixtureresources/__init__.py
src/fixtureresources/_version.py
src/fixtureresources/fixtures.py
src/fixtureresources/mockfile.py
src/fixtureresources.egg-info/PKG-INFO
src/fixtureresources.egg-info/SOURCES.txt
src/fixtureresources.egg-info/dependency_links.txt
src/fixtureresources.egg-info/requires.txt
src/fixtureresources.egg-info/top_level.txt
tests/test_fixtures.py
tests/test_mockfile.py