Metadata-Version: 1.1
Name: fixtureresources
Version: 1.0
Summary: Commonly useful pytest fixtures and mocks.
Home-page: https://github.com/nokia/fixtureresources
Author: Petri Huovinen
Author-email: petri.huovinen@nokia.com
License: BSD 3-Clause
Keywords: pytest
Platform: UNKNOWN
Classifier: Intended Audience :: Developers
Classifier: License :: OSI Approved :: BSD License
Classifier: Programming Language :: Python :: 2
Classifier: Programming Language :: Python :: 2.7
Classifier: Programming Language :: Python :: 3
Classifier: Programming Language :: Python :: 3.6
Classifier: Topic :: Software Development
